{
  "type": "mekanism:purifying",
  "conditions": [
    {
      "value": {
        "tag": "forge:ores/green_sapphire",
        "type": "forge:tag_empty"
      },
      "type": "forge:not"
    },
    {
      "materialType": "green_sapphire",
      "requireLevel": 3,
      "type": "moremekanismprocessing:processing_level"
    }
  ],
  "itemInput": {
    "ingredient": {
      "tag": "forge:ores/green_sapphire"
    }
  },
  "chemicalInput": {
    "amount": 1,
    "gas": "mekanism:oxygen"
  },
  "output": {
    "item": "moremekanismprocessing:clump_green_sapphire",
    "count": 3
  }
}