{
  "neoforge:conditions": [
    {
      "type": "neoforge:not",
      "value": {
        "type": "neoforge:tag_empty",
        "tag": "forge:raw_materials/draconium"
      }
    },
    {
      "type": "moremekanismprocessing:processing_level",
      "materialType": "draconium",
      "requireLevel": 3
    }
  ],
  "type": "mekanism:purifying",
  "chemicalInput": {
    "amount": 1,
    "gas": "mekanism:oxygen"
  },
  "itemInput": {
    "ingredient": {
      "tag": "forge:raw_materials/draconium"
    }
  },
  "output": {
    "count": 2,
    "item": "moremekanismprocessing:clump_draconium"
  }
}